dixa/__init__.py
dixa/client.py
dixa/exceptions.py
dixa/api/__init__.py
dixa/api/v1/__init__.py
dixa/api/v1/agents.py
dixa/api/v1/analytics.py
dixa/api/v1/contact_endpoints.py
dixa/api/v1/conversations.py
dixa/api/v1/custom_attributes.py
dixa/api/v1/end_users.py
dixa/api/v1/queues.py
dixa/api/v1/tags.py
dixa/api/v1/teams.py
dixa/api/v1/webhooks.py
dixa/model/__init__.py
dixa/model/v1/__init__.py
dixa/model/v1/activity_log.py
dixa/model/v1/agent.py
dixa/model/v1/analytics.py
dixa/model/v1/anonymization.py
dixa/model/v1/bulk_action.py
dixa/model/v1/contact_endpoint.py
dixa/model/v1/conversation.py
dixa/model/v1/custom_attribute.py
dixa/model/v1/end_user.py
dixa/model/v1/internal_note.py
dixa/model/v1/message.py
dixa/model/v1/queue.py
dixa/model/v1/tag.py
dixa/model/v1/team.py
dixa/model/v1/webhook_subscription.py
dixa_api_client-2.4.12.dist-info/licenses/LICENSE
dixa_api_client-2.4.12.dist-info/METADATA
dixa_api_client-2.4.12.dist-info/WHEEL
dixa_api_client-2.4.12.dist-info/top_level.txt
dixa_api_client-2.4.12.dist-info/RECORD
