Metadata-Version: 2.4
Name: dixa-api-client
Version: 2.4.12
Summary: Python API Client for Dixa
Author-email: ChemicalLuck <j.tebbett@outlook.com>
License-Expression: MIT
Project-URL: Homepage, https://github.com/ChemicalLuck/dixa-api
Project-URL: Source, https://github.com/ChemicalLuck/dixa-api
Keywords: Dixa,API,client,customer support,python
Classifier: Development Status :: 5 - Production/Stable
Classifier: Intended Audience :: Developers
Classifier: Natural Language :: English
Classifier: Programming Language :: Python
Classifier: Programming Language :: Python :: 3
Classifier: Programming Language :: Python :: 3 :: Only
Classifier: Programming Language :: Python :: 3.8
Classifier: Programming Language :: Python :: 3.9
Classifier: Programming Language :: Python :: 3.10
Classifier: Programming Language :: Python :: 3.11
Classifier: Programming Language :: Python :: 3.12
Classifier: Programming Language :: Python :: 3.13
Classifier: Topic :: Software Development :: Libraries :: Python Modules
Requires-Python: >=3.8
License-File: LICENSE
Requires-Dist: requests
Provides-Extra: dev
Requires-Dist: ruff; extra == "dev"
Requires-Dist: pre-commit; extra == "dev"
Requires-Dist: python-dotenv; extra == "dev"
Requires-Dist: vermin; extra == "dev"
Dynamic: license-file
